yurenizer/__init__.py
yurenizer/csv_normalizer.py
yurenizer/data/.gitkeep
yurenizer/data/custom_synonyms.csv
yurenizer/data/custom_synonyms.json
yurenizer/data/custom_synonyms.tsv
yurenizer/entities/__init__.py
yurenizer/entities/flg_option.py
yurenizer/entities/normalizer.py
yurenizer/entities/sudachi_dict.py
yurenizer/entities/synonym.py
yurenizer/loaders.py
yurenizer/normalizer.py
yurenizer-0.2.2.dist-info/LICENSE
yurenizer-0.2.2.dist-info/METADATA
yurenizer-0.2.2.dist-info/WHEEL
yurenizer-0.2.2.dist-info/entry_points.txt
yurenizer-0.2.2.dist-info/RECORD
