Metadata-Version: 2.1
Name: yurenizer
Version: 0.2.2
Summary: A library for standardizing terms with spelling variations using a synonym dictionary.
Home-page: https://github.com/sea-turt1e/yurenizer
License: Apache-2.0
Keywords: nlp,text-processing,japanese,synonym,normalization
Author: sea-turt1e
Author-email: h.yamada.bg@gmail.com
Requires-Python: >=3.11,<4.0
Classifier: License :: OSI Approved :: Apache Software License
Classifier: Programming Language :: Python :: 3
Classifier: Programming Language :: Python :: 3.11
Classifier: Programming Language :: Python :: 3.12
Classifier: Programming Language :: Python :: 3.13
Requires-Dist: sudachidict-full
Requires-Dist: sudachipy (>=0.6.8)
Project-URL: Repository, https://github.com/sea-turt1e/yurenizer
